rgb2ansi.py
rgb2ansi-1.0.1.dist-info/DESCRIPTION.rst
rgb2ansi-1.0.1.dist-info/METADATA
rgb2ansi-1.0.1.dist-info/RECORD
rgb2ansi-1.0.1.dist-info/WHEEL
rgb2ansi-1.0.1.dist-info/metadata.json
rgb2ansi-1.0.1.dist-info/top_level.txt
