Metadata-Version: 2.0
Name: rgb2ansi
Version: 1.0.1
Summary: Color strings for terminal ouput (ANSI 256 colors) using CSS-style ``rgb`` notation.
Home-page: https://github.com/brutasse/rgb2ansi
Author: Bruno Renié
Author-email: UNKNOWN
License: BSD
Platform: UNKNOWN
Classifier: Intended Audience :: Developers
Classifier: Intended Audience :: System Administrators
Classifier: License :: OSI Approved :: BSD License
Classifier: Operating System :: Unix
Classifier: Programming Language :: Python
Classifier: Programming Language :: Python :: 3 :: Only
Classifier: Development Status :: 5 - Production/Stable
Classifier: Environment :: Console
Requires-Python: >=3.6
